setup.py
wayround_org/toxcorebind/__init__.py
wayround_org/toxcorebind/tox.pyx
wayround_org/toxcorebind/tox_h.pxd
wayround_org_toxcorebind.egg-info/PKG-INFO
wayround_org_toxcorebind.egg-info/SOURCES.txt
wayround_org_toxcorebind.egg-info/dependency_links.txt
wayround_org_toxcorebind.egg-info/requires.txt
wayround_org_toxcorebind.egg-info/top_level.txt