Metadata-Version: 1.1
Name: wayround-org-toxcorebind
Version: 0.6
Summary: Python toxcore binding
Home-page: https://github.com/AnimusPEXUS/wayround_org_toxcorebind
Author: Alexey Gorshkov
Author-email: animus@wayround.org
License: UNKNOWN
Platform: UNKNOWN
Classifier: License :: OSI Approved :: GNU General Public License v3 or later (GPLv3+)
Classifier: Operating System :: POSIX
